torchadversarial/__init__.py
torchadversarial/attack.py
torchadversarial/fgsm.py
torchadversarial-0.0.2.dist-info/licenses/LICENSE
torchadversarial-0.0.2.dist-info/METADATA
torchadversarial-0.0.2.dist-info/WHEEL
torchadversarial-0.0.2.dist-info/top_level.txt
torchadversarial-0.0.2.dist-info/zip-safe
torchadversarial-0.0.2.dist-info/RECORD
