Metadata-Version: 2.4
Name: torchadversarial
Version: 0.0.2
Home-page: https://github.com/cat-claws/torchadversarial
Author: cat-claws
Author-email: 47313357+cat-claws@users.noreply.github.com
License: MIT
Classifier: Programming Language :: Python
Classifier: Programming Language :: Python :: 3
License-File: LICENSE
Dynamic: author
Dynamic: author-email
Dynamic: classifier
Dynamic: description
Dynamic: description-content-type
Dynamic: home-page
Dynamic: license
Dynamic: license-file
